LICENSE.txt
README.md
setup.cfg
setup.py
fortosto/__init__.py
fortosto/fortosto.py
fortosto/initializer.py
fortosto/main.py
fortosto/properties.py
fortosto.egg-info/PKG-INFO
fortosto.egg-info/SOURCES.txt
fortosto.egg-info/dependency_links.txt
fortosto.egg-info/requires.txt
fortosto.egg-info/top_level.txt
fortosto/commons/CastDataType.py
fortosto/commons/FileType.py
fortosto/commons/InitializationResult.py
fortosto/commons/PostgresCastException.py
fortosto/commons/PostgresException.py
fortosto/commons/TableNormalizer.py
fortosto/commons/UnableToSaveException.py
fortosto/commons/UnexpectedEnumValueException.py
fortosto/commons/Utils.py
fortosto/commons/castingUtils.py
fortosto/commons/dao.py
fortosto/commons/dateParser.py
fortosto/commons/loggingUtils.py
fortosto/commons/sqlTemplates.py
fortosto/commons/stringsNormalizer.py