Metadata-Version: 1.2
Name: fortosto
Version: 1.1.0
Summary: csv 2 pg loader
Home-page: https://github.com/halx4/fortosto
Author: halx4
Author-email: foivoschrist@outlook.com
License: MIT
Download-URL: https://github.com/halx4/fortosto/archive/refs/tags/v1.0.0.tar.gz
Keywords: CSV,POSTGRES,LOAD
Platform: UNKNOWN
Classifier: Development Status :: 4 - Beta
Classifier: Intended Audience :: Developers
Classifier: Intended Audience :: System Administrators
Classifier: Intended Audience :: Information Technology
Classifier: Topic :: Database
Classifier: Topic :: Software Development
Classifier: License :: OSI Approved :: MIT License
Classifier: Programming Language :: Python :: 3
Classifier: Programming Language :: Python :: 3.7
Classifier: Programming Language :: Python :: 3.8
Classifier: Programming Language :: Python :: 3.9
Requires-Python: >=3.7
